odoo8_addon_portal_partner_merge-8.0.1.0.0.99.dev5-py2.7-nspkg.pth
odoo8_addon_portal_partner_merge-8.0.1.0.0.99.dev5.dist-info/METADATA
odoo8_addon_portal_partner_merge-8.0.1.0.0.99.dev5.dist-info/RECORD
odoo8_addon_portal_partner_merge-8.0.1.0.0.99.dev5.dist-info/WHEEL
odoo8_addon_portal_partner_merge-8.0.1.0.0.99.dev5.dist-info/namespace_packages.txt
odoo8_addon_portal_partner_merge-8.0.1.0.0.99.dev5.dist-info/top_level.txt
odoo_addons/portal_partner_merge/__init__.py
odoo_addons/portal_partner_merge/__openerp__.py
odoo_addons/portal_partner_merge/i18n/de.po
odoo_addons/portal_partner_merge/i18n/es.po
odoo_addons/portal_partner_merge/i18n/portal_partner_merge.pot
odoo_addons/portal_partner_merge/i18n/pt_BR.po
odoo_addons/portal_partner_merge/i18n/sl.po
odoo_addons/portal_partner_merge/static/description/icon.png
odoo_addons/portal_partner_merge/wizard/__init__.py
odoo_addons/portal_partner_merge/wizard/portal_wizard.py
